setup.py
webassets_livescript/__init__.py
webassets_livescript.egg-info/PKG-INFO
webassets_livescript.egg-info/SOURCES.txt
webassets_livescript.egg-info/dependency_links.txt
webassets_livescript.egg-info/requires.txt
webassets_livescript.egg-info/top_level.txt