Metadata-Version: 1.1
Name: webassets-livescript
Version: 0.1
Summary: webassets livescript filter
Home-page: http://github.com/jorgebg/webassets-livescript
Author: Jorge Barata Gonzalez
Author-email: jorgebg
License: MIT
Download-URL: http://github.com/jorgebg/webassets-livescript
Platform: UNKNOWN
